README.md
setup.py
Flask_Philo.egg-info/PKG-INFO
Flask_Philo.egg-info/SOURCES.txt
Flask_Philo.egg-info/dependency_links.txt
Flask_Philo.egg-info/entry_points.txt
Flask_Philo.egg-info/requires.txt
Flask_Philo.egg-info/top_level.txt
flask_philo/__init__.py
flask_philo/admin.py
flask_philo/auth.py
flask_philo/default_settings.py
flask_philo/exceptions.py
flask_philo/serializers.py
flask_philo/test.py
flask_philo/utils.py
flask_philo/views.py
flask_philo/cloud/__init__.py
flask_philo/cloud/aws/__init__.py
flask_philo/cloud/aws/key_pair.py
flask_philo/cloud/aws/s3.py
flask_philo/cloud/aws/s3api.py
flask_philo/cloud/aws/sqs.py
flask_philo/cloud/aws/utils.py
flask_philo/commands_flask_philo/__init__.py
flask_philo/commands_flask_philo/aws.py
flask_philo/commands_flask_philo/gen_salt.py
flask_philo/commands_flask_philo/runserver.py
flask_philo/commands_flask_philo/runuwsgi.py
flask_philo/commands_flask_philo/syncdb.py
flask_philo/commands_flask_philo/test.py
flask_philo/db/__init__.py
flask_philo/db/exceptions.py
flask_philo/db/elasticsearch/__init__.py
flask_philo/db/elasticsearch/client.py
flask_philo/db/elasticsearch/connection.py
flask_philo/db/postgresql/__init__.py
flask_philo/db/postgresql/connection.py
flask_philo/db/postgresql/orm.py
flask_philo/db/postgresql/schema.py
flask_philo/db/postgresql/types.py
flask_philo/db/redis/__init__.py
flask_philo/db/redis/client.py
flask_philo/db/redis/connection.py
flask_philo/jinja2/__init__.py
flask_philo/templates/README.md
flask_philo/templates/__init__.py
flask_philo/templates/base.txt
flask_philo/templates/dev.txt
flask_philo/templates/development.py
flask_philo/templates/example_views.py
flask_philo/templates/manage.py
flask_philo/templates/test.py
flask_philo/templates/test_views.py
flask_philo/templates/urls.py