Metadata-Version: 1.2
Name: Flask-Philo
Version: 3.7.1
Summary: Simple web framework based on Flask
Home-page: https://github.com/Riffstation/flask-philo
Author: Manuel Ignacio Franco Galeano
Author-email: maigfrga@gmail.com
License: Apache
Keywords: web framework flask microservice
Platform: UNKNOWN
Classifier: Development Status :: 5 - Production/Stable
Classifier: Intended Audience :: Developers
Classifier: Topic :: Software Development
Classifier: Framework :: Flask
Classifier: Programming Language :: Python :: 3
Requires-Python: >=3
